osis2usfm/__init__.py
osis2usfm-1.2.dist-info/DESCRIPTION.rst
osis2usfm-1.2.dist-info/METADATA
osis2usfm-1.2.dist-info/RECORD
osis2usfm-1.2.dist-info/WHEEL
osis2usfm-1.2.dist-info/metadata.json
osis2usfm-1.2.dist-info/top_level.txt
