Metadata-Version: 2.0
Name: osis2usfm
Version: 1.2
Summary: Convert a list of OSIS references to USFM.
Home-page: https://github.com/bbelyeu/osis2usfm
Author: Brad Belyeu
Author-email: bradleylamar@gmail.com
License: MIT
Download-URL: https://github.com/bbelyeu/osis2usfm/archive/1.2.zip
Keywords: OSIS,USFM,bible
Platform: any
Classifier: Environment :: Web Environment
Classifier: Intended Audience :: Developers
Classifier: License :: OSI Approved :: MIT License
Classifier: Operating System :: OS Independent
Classifier: Programming Language :: Python
Classifier: Programming Language :: Python :: 3
Classifier: Topic :: Internet :: WWW/HTTP :: Dynamic Content
Classifier: Topic :: Software Development :: Libraries :: Python Modules
Requires-Dist: Flask
